{
    "dialogue_id": "11-02",
    "title": "我想租房子",
    "participants": ["如玉", "房東"],
    "video_url": "https://www.youtube.com/watch?v=pjO8pwYmIkg&list=PLzhEEEIeppr9DGKlQJeZglps1ubDHUE0x&index=4",
    "vocabulary_video_url": "https://www.youtube.com/watch?v=wdLosXBshrE&list=PLzhEEEIeppr9DGKlQJeZglps1ubDHUE0x&index=5",
    "content": [
        {
            "speaker": "如玉",
            "text": "喂，房東先生，你好，我是白如玉，你收到我的房租了嗎？"
        },
        {
            "speaker": "房東",
            "text": "我已經收到了，謝謝。妳習慣了嗎？"
        },
        {
            "speaker": "如玉",
            "text": "習慣了。可是，有一個問題，熱水器的水好像不熱。"
        },
        {
            "speaker": "房東",
            "text": "今天我會去看看。妳什麼時候有空？晚上可以嗎？"
        },
        {
            "speaker": "如玉",
            "text": "不好意思，今天晚上我有事。"
        },
        {
            "speaker": "房東",
            "text": "沒關係，明天下午呢？"
        },
        {
            "speaker": "如玉",
            "text": "好，我在家等你。"
        },
        {
            "speaker": "房東",
            "text": "那我明天下午兩點到。還有問題嗎？"
        },
        {
            "speaker": "如玉",
            "text": "我想買電視。請問可以幫我裝有線電視嗎？"
        },
        {
            "speaker": "房東",
            "text": "可以，不過妳得自己付錢。"
        },
        {
            "speaker": "如玉",
            "text": "好的，謝謝你。"
        }
    ],
    "lesson_number": 11
}
